vilya/__init__.py
vilya/records.py
vilya/utils.py
vilya/vilya.py
vilya-0.1.0.dev10.data/data/vilya/config.toml
vilya-0.1.0.dev10.dist-info/LICENSE
vilya-0.1.0.dev10.dist-info/METADATA
vilya-0.1.0.dev10.dist-info/WHEEL
vilya-0.1.0.dev10.dist-info/entry_points.txt
vilya-0.1.0.dev10.dist-info/top_level.txt
vilya-0.1.0.dev10.dist-info/RECORD
